{
  "companyRoles": [
    {
      "companyRole": "ACTIVE_PARTICIPANT",
      "descriptions": {
        "additionalProp1": "string",
        "additionalProp2": "string",
        "additionalProp3": "string"
      },
      "agreementIds": [
        "3fa85f64-5717-4562-b3fc-2c963f66afa6"
      ]
    }
  ],
  "agreements": [
    {
      "agreementId": "3fa85f64-5717-4562-b3fc-2c963f66afa6",
      "name": "string",
      "agreementLink": "string",
      "documentId": "3fa85f64-5717-4562-b3fc-2c963f66afa6"
    }
  ]
}